mtpy/__init__.py
mtpy/mtpy_globals.py
mtpy/analysis/__init__.py
mtpy/analysis/residual_phase_tensor.py
mtpy/core/__init__.py
mtpy/core/mt.py
mtpy/core/mt_collection.py
mtpy/core/mt_data.py
mtpy/core/mt_dataframe.py
mtpy/core/mt_location.py
mtpy/core/mt_stations.py
mtpy/core/transfer_function/__init__.py
mtpy/core/transfer_function/base.py
mtpy/core/transfer_function/pt.py
mtpy/core/transfer_function/tipper.py
mtpy/core/transfer_function/z.py
mtpy/core/transfer_function/z_analysis/__init__.py
mtpy/core/transfer_function/z_analysis/distortion.py
mtpy/core/transfer_function/z_analysis/niblettbostick.py
mtpy/core/transfer_function/z_analysis/zinvariants.py
mtpy/gis/__init__.py
mtpy/gis/raster_tools.py
mtpy/gis/shapefile_creator.py
mtpy/imaging/__init__.py
mtpy/imaging/mtcolors.py
mtpy/imaging/plot_mt_response.py
mtpy/imaging/plot_mt_responses.py
mtpy/imaging/plot_penetration_depth_1d.py
mtpy/imaging/plot_penetration_depth_map.py
mtpy/imaging/plot_phase_tensor_maps.py
mtpy/imaging/plot_phase_tensor_pseudosection.py
mtpy/imaging/plot_pseudosection.py
mtpy/imaging/plot_pt.py
mtpy/imaging/plot_residual_pt_maps.py
mtpy/imaging/plot_residual_pt_ps.py
mtpy/imaging/plot_resphase_maps.py
mtpy/imaging/plot_spectrogram.py
mtpy/imaging/plot_stations.py
mtpy/imaging/plot_strike.py
mtpy/imaging/mtplot_tools/__init__.py
mtpy/imaging/mtplot_tools/arrows.py
mtpy/imaging/mtplot_tools/base.py
mtpy/imaging/mtplot_tools/ellipses.py
mtpy/imaging/mtplot_tools/map_interpolation_tools.py
mtpy/imaging/mtplot_tools/plot_settings.py
mtpy/imaging/mtplot_tools/plotters.py
mtpy/imaging/mtplot_tools/utils.py
mtpy/modeling/__init__.py
mtpy/modeling/errors.py
mtpy/modeling/gocad.py
mtpy/modeling/mare2dem.py
mtpy/modeling/mesh_tools.py
mtpy/modeling/pek1d.py
mtpy/modeling/pek1dclasses.py
mtpy/modeling/pek2d.py
mtpy/modeling/pek2dforward.py
mtpy/modeling/structured_mesh_3d.py
mtpy/modeling/winglink.py
mtpy/modeling/winglinktools.py
mtpy/modeling/modem/__init__.py
mtpy/modeling/modem/config.py
mtpy_v2-2.0.14.dist-info/licenses/LICENSE
mtpy_v2-2.0.14.dist-info/METADATA
mtpy_v2-2.0.14.dist-info/WHEEL
mtpy_v2-2.0.14.dist-info/top_level.txt
mtpy_v2-2.0.14.dist-info/RECORD
