Metadata-Version: 2.4
Name: mtpy-v2
Version: 2.0.14
Summary: Python toolkit for standard magnetotelluric data processing.
Author: Alison Kirkby, Fei Zhang, Rakib Hassan, Lars Krieger, Stephan Thiel
Author-email: Jared Peacock <jpeacock@usgs.gov>
License: MIT License
Project-URL: Homepage, https://github.com/MTgeophysics/mtpy-v2
Project-URL: Repository, https://github.com/MTgeophysics/mtpy-v2
Keywords: magnetotellurics
Classifier: Development Status :: 5 - Production/Stable
Classifier: Intended Audience :: Developers
Classifier: License :: OSI Approved :: MIT License
Classifier: Natural Language :: English
Classifier: Programming Language :: Python :: 3
Classifier: Programming Language :: Python :: 3.10
Classifier: Programming Language :: Python :: 3.11
Classifier: Programming Language :: Python :: 3.12
Requires-Python: >=3.10
License-File: LICENSE
Requires-Dist: numpy
Requires-Dist: scipy
Requires-Dist: xarray
Requires-Dist: matplotlib
Requires-Dist: pyproj
Requires-Dist: configparser
Requires-Dist: mt_metadata
Requires-Dist: mth5
Requires-Dist: geopandas
Requires-Dist: rasterio
Requires-Dist: contextily
Requires-Dist: pyevtk
Requires-Dist: simpeg
Requires-Dist: aurora
Provides-Extra: test
Requires-Dist: pytest>=3; extra == "test"
Requires-Dist: pytest-cov; extra == "test"
Requires-Dist: pytest-mock; extra == "test"
Requires-Dist: pytest-subtests; extra == "test"
Requires-Dist: pytest-xdist; extra == "test"
Dynamic: license-file
